drive_backup_credentials/credentials.cpython-311-darwin.so
drive_backup_credentials-0.2.1.dist-info/RECORD
drive_backup_credentials-0.2.1.dist-info/LICENSE
drive_backup_credentials-0.2.1.dist-info/WHEEL
drive_backup_credentials-0.2.1.dist-info/top_level.txt
drive_backup_credentials-0.2.1.dist-info/METADATA
