Metadata-Version: 2.1
Name: drive-backup-credentials
Version: 0.2.1
Summary: Drive Backup credential tool module.
Author-email: George Waters <gwatersdev@gmail.com>
License: Copyright (c) 2024 George Waters
Requires-Python: >=3.8
License-File: LICENSE
Requires-Dist: cryptography >=42.0.0
Requires-Dist: google-auth-oauthlib >=1.0.0
